cli.py
elastic_wikidata/__init__.py
elastic_wikidata/__metadata__.py
elastic_wikidata/config.py
elastic_wikidata/dump_to_es.py
elastic_wikidata/http.py
elastic_wikidata/sparql_helpers.py
elastic_wikidata/sparql_to_es.py
elastic_wikidata/wd_entities.py
elastic_wikidata-1.0.1.dist-info/LICENSE.txt
elastic_wikidata-1.0.1.dist-info/METADATA
elastic_wikidata-1.0.1.dist-info/WHEEL
elastic_wikidata-1.0.1.dist-info/entry_points.txt
elastic_wikidata-1.0.1.dist-info/top_level.txt
elastic_wikidata-1.0.1.dist-info/RECORD
