Metadata-Version: 2.1
Name: elastic-wikidata
Version: 1.0.1
Summary: elastic-wikidata
Home-page: https://github.com/TheScienceMuseum/elastic-wikidata
Author: Science Museum Group
License: UNKNOWN
Download-URL: https://github.com/TheScienceMuseum/elastic-wikidata/archive/v1.0.1.tar.gz
Platform: UNKNOWN
Classifier: Programming Language :: Python :: 3
Classifier: License :: OSI Approved :: MIT License
Classifier: Operating System :: OS Independent
Requires-Python: >=3.6
License-File: LICENSE.txt
Requires-Dist: click (==7.1.2)
Requires-Dist: elasticsearch (==7.8.1)
Requires-Dist: SPARQLWrapper (==1.8.5)
Requires-Dist: tqdm (>=4.48.2)
Requires-Dist: requests (==2.24.0)
